code_contracts-0.1.1.dist-info/DESCRIPTION.rst
code_contracts-0.1.1.dist-info/METADATA
code_contracts-0.1.1.dist-info/RECORD
code_contracts-0.1.1.dist-info/WHEEL
code_contracts-0.1.1.dist-info/metadata.json
code_contracts-0.1.1.dist-info/top_level.txt
contracts/__init__.py
contracts/assertion.py
contracts/contract.py
