Metadata-Version: 2.0
Name: code-contracts
Version: 0.1.1
Summary: A library that provides code contracts and assertions.
Home-page: https://github.com/mbenbernard/contracts
Author: Benoit Bernard
Author-email: aGlAYmVuYmVybmFyZGJsb2cuY29t@base64.email
License: Apache 2.0
Platform: UNKNOWN
Classifier: Development Status :: 4 - Beta
Classifier: Intended Audience :: Developers
Classifier: Natural Language :: English
Classifier: License :: OSI Approved :: Apache Software License
Classifier: Programming Language :: Python
Classifier: Programming Language :: Python :: 3
Classifier: Programming Language :: Python :: 3.3
Classifier: Programming Language :: Python :: 3.4
Classifier: Programming Language :: Python :: 3.5
Classifier: Programming Language :: Python :: 3.6
Classifier: Programming Language :: Python :: Implementation :: CPython
Classifier: Programming Language :: Python :: Implementation :: PyPy
Requires-Python: ~=3.3
